deepcorrect/__init__.py
deepcorrect/deepcorrect.py
deepcorrect-1.0.5.dist-info/LICENSE
deepcorrect-1.0.5.dist-info/METADATA
deepcorrect-1.0.5.dist-info/WHEEL
deepcorrect-1.0.5.dist-info/top_level.txt
deepcorrect-1.0.5.dist-info/RECORD
