Metadata-Version: 2.1
Name: deepcorrect
Version: 1.0.5
Summary: Text Correction wth deep learning
Home-page: https://github.com/bedapudi6788/deepcorrect
Author: BEDAPUDI PRANEETH
Author-email: praneethbedapudi@gmail.com
License: GPLv3
Platform: UNKNOWN
Classifier: License :: OSI Approved :: GNU General Public License v3 (GPLv3)
Classifier: Programming Language :: Python
Classifier: Programming Language :: Python :: 3
Classifier: Programming Language :: Python :: 3.6
Classifier: Programming Language :: Python :: Implementation :: CPython
Classifier: Programming Language :: Python :: Implementation :: PyPy
Requires-Python: >=3.6.0
Requires-Dist: txt2txt (==1.0.9)
